poclab/__init__.py
poclab-0.0.6.dist-info/LICENSE
poclab-0.0.6.dist-info/METADATA
poclab-0.0.6.dist-info/WHEEL
poclab-0.0.6.dist-info/top_level.txt
poclab-0.0.6.dist-info/RECORD
