Metadata-Version: 2.1
Name: poclab
Version: 0.0.6
Summary: A place for POCs to be born and toddler around until they can walk on their own
Home-page: https://github.com/i2mint/poclab
License: mit
Platform: any
License-File: LICENSE
